saltext/formula/__init__.py
saltext/formula/version.py
saltext/formula/modules/__init__.py
saltext/formula/modules/map.py
saltext/formula/wrapper/__init__.py
saltext/formula/wrapper/map.py
saltext.formula-0.3.0.dist-info/LICENSE
saltext.formula-0.3.0.dist-info/METADATA
saltext.formula-0.3.0.dist-info/NOTICE
saltext.formula-0.3.0.dist-info/WHEEL
saltext.formula-0.3.0.dist-info/entry_points.txt
saltext.formula-0.3.0.dist-info/top_level.txt
saltext.formula-0.3.0.dist-info/RECORD
